file_import/__init__.py
file_import/file_import.py
file_import-0.1.dist-info/DESCRIPTION.rst
file_import-0.1.dist-info/METADATA
file_import-0.1.dist-info/RECORD
file_import-0.1.dist-info/WHEEL
file_import-0.1.dist-info/metadata.json
file_import-0.1.dist-info/top_level.txt
