Metadata-Version: 2.0
Name: file-import
Version: 0.1
Summary: Directly import Python files
Home-page: https://github.com/rbnvrw/file_import
Author: Ruben Verweij
Author-email: rbnvrw@gmail.com
License: MIT
Platform: UNKNOWN
